Adyen/__init__.py
Adyen/client.py
Adyen/exceptions.py
Adyen/httpclient.py
Adyen/settings.py
Adyen/util.py
Adyen/services/__init__.py
Adyen/services/balanceControl.py
Adyen/services/base.py
Adyen/services/binlookup.py
Adyen/services/dataProtection.py
Adyen/services/disputes.py
Adyen/services/posMobile.py
Adyen/services/recurring.py
Adyen/services/storedValue.py
Adyen/services/terminal.py
Adyen/services/balancePlatform/__init__.py
Adyen/services/balancePlatform/account_holders_api.py
Adyen/services/balancePlatform/balance_accounts_api.py
Adyen/services/balancePlatform/bank_account_validation_api.py
Adyen/services/balancePlatform/card_orders_api.py
Adyen/services/balancePlatform/grant_accounts_api.py
Adyen/services/balancePlatform/grant_offers_api.py
Adyen/services/balancePlatform/manage_card_pin_api.py
Adyen/services/balancePlatform/manage_sca_devices_api.py
Adyen/services/balancePlatform/network_tokens_api.py
Adyen/services/balancePlatform/payment_instrument_groups_api.py
Adyen/services/balancePlatform/payment_instruments_api.py
Adyen/services/balancePlatform/platform_api.py
Adyen/services/balancePlatform/transaction_rules_api.py
Adyen/services/balancePlatform/transfer_routes_api.py
Adyen/services/checkout/__init__.py
Adyen/services/checkout/donations_api.py
Adyen/services/checkout/modifications_api.py
Adyen/services/checkout/orders_api.py
Adyen/services/checkout/payment_links_api.py
Adyen/services/checkout/payments_api.py
Adyen/services/checkout/recurring_api.py
Adyen/services/checkout/utility_api.py
Adyen/services/legalEntityManagement/__init__.py
Adyen/services/legalEntityManagement/business_lines_api.py
Adyen/services/legalEntityManagement/documents_api.py
Adyen/services/legalEntityManagement/hosted_onboarding_api.py
Adyen/services/legalEntityManagement/legal_entities_api.py
Adyen/services/legalEntityManagement/pci_questionnaires_api.py
Adyen/services/legalEntityManagement/tax_e_delivery_consent_api.py
Adyen/services/legalEntityManagement/terms_of_service_api.py
Adyen-13.2.0.dist-info/LICENSE.md
Adyen-13.2.0.dist-info/METADATA
Adyen-13.2.0.dist-info/WHEEL
Adyen-13.2.0.dist-info/top_level.txt
Adyen-13.2.0.dist-info/RECORD
